yta_ai/__init__.py
yta_ai/blip.py
yta_ai/experimental/__init__.py
yta_ai/experimental/chat_assistant/__init__.py
yta_ai/experimental/chat_assistant/ai21.py
yta_ai/experimental/chat_assistant/chat_gpt.py
yta_ai/experimental/chat_assistant/prompts.py
yta_ai/experimental/generation/__init__.py
yta_ai/experimental/generation/image/__init__.py
yta_ai/experimental/generation/image/aifumes.py
yta_ai/experimental/generation/music/__init__.py
yta_ai/experimental/generation/music/tuna_voicemod.py
yta_ai/experimental/narration_script_generator.py
yta_ai/experimental/transcription.py
yta_ai/flux.py
yta_ai/gemini.py
yta_ai/hugginface.py
yta_ai/leonardo.py
yta_ai/llava.py
yta_ai/openai.py
yta_ai/pollinations.py
yta_ai/prodia.py
yta_ai/prompts/__init__.py
yta_ai/prompts/religious.py
yta_ai-0.0.11.dist-info/LICENSE
yta_ai-0.0.11.dist-info/METADATA
yta_ai-0.0.11.dist-info/WHEEL
yta_ai-0.0.11.dist-info/RECORD
