Metadata-Version: 2.3
Name: yta-ai
Version: 0.0.11
Summary: Youtube Autónomo AI Module.
Author: danialcala94
Author-email: danielalcalavalera@gmail.com
Requires-Python: ==3.9
Classifier: Programming Language :: Python :: 3
Classifier: Programming Language :: Python :: 3.9
Requires-Dist: yta_ai_blip (>=0.0.1,<1.0.0)
Requires-Dist: yta_ai_flux (>=0.0.1,<1.0.0)
Requires-Dist: yta_ai_gemini (>=0.0.1,<1.0.0)
Requires-Dist: yta_ai_hugginface (>=0.0.1,<1.0.0)
Requires-Dist: yta_ai_leonardo (>=0.0.1,<1.0.0)
Requires-Dist: yta_ai_llava (>=0.0.1,<1.0.0)
Requires-Dist: yta_ai_openai (>=0.0.1,<1.0.0)
Requires-Dist: yta_ai_pollinations (>=0.0.1,<1.0.0)
Requires-Dist: yta_ai_prodia (>=0.0.1,<1.0.0)
Requires-Dist: yta_constants (>=0.0.1,<1.0.0)
